telegram/__init__.py
telegram/dispatcher.py
telegram/handlers.py
telegram/types.py
telegram/updater.py
vohid_telegram_bot-0.1.0.dist-info/METADATA
vohid_telegram_bot-0.1.0.dist-info/WHEEL
vohid_telegram_bot-0.1.0.dist-info/top_level.txt
vohid_telegram_bot-0.1.0.dist-info/RECORD
