Metadata-Version: 2.4
Name: vohid-telegram-bot
Version: 0.1.0
Summary: A simple python telegram library
Home-page: https://github.com/VOHID2308/py-gram-bot.git
Author: Vohid_23
Classifier: Programming Language :: Python :: 3
Classifier: License :: OSI Approved :: MIT License
Classifier: Operating System :: OS Independent
Requires-Python: >=3.9
Dynamic: author
Dynamic: classifier
Dynamic: description
Dynamic: description-content-type
Dynamic: home-page
Dynamic: requires-python
Dynamic: summary
